Pixseal/simpleImage_py.py
Pixseal/simpleImage_ext.cpython-310-i386-linux-gnu.so
Pixseal/keyInput.py
Pixseal/imageValidator.py
Pixseal/simpleImage.py
Pixseal/imageSigner.py
Pixseal/__init__.py
pixseal-1.1.1.dist-info/WHEEL
pixseal-1.1.1.dist-info/top_level.txt
pixseal-1.1.1.dist-info/METADATA
pixseal-1.1.1.dist-info/RECORD
