Metadata-Version: 2.1
Name: Pixseal
Version: 1.1.1
Summary: Image integrity and authenticity verification tool
Requires-Python: >=3.8
Requires-Dist: cryptography>=41.0.0
